nsj_pyRPA/__init__.py
nsj_pyRPA/app.py
nsj_pyRPA/company_editor.py
nsj_pyRPA/main.py
nsj_pyRPA/notification_team_editor.py
nsj_pyRPA/notification_teams_app.py
nsj_pyRPA/pyRPA.py
nsj_pyRPA/dto/__init__.py
nsj_pyRPA/dto/company_dto.py
nsj_pyRPA/dto/jobschedule_dto.py
nsj_pyRPA/dto/notification_team_dto.py
nsj_pyRPA/nasajonRPA/__init__.py
nsj_pyRPA/nasajonRPA/orquestrador.py
nsj_pyRPA/nasajonRPA/automacoes/AbstractAutomacao.py
nsj_pyRPA/nasajonRPA/automacoes/__init__.py
nsj_pyRPA/nasajonRPA/automacoes/processamentocalculoadiantamentofolha.py
nsj_pyRPA/nasajonRPA/automacoes/processamentocalculoferias.py
nsj_pyRPA/nasajonRPA/automacoes/processamentocalculofolha.py
nsj_pyRPA/nasajonRPA/automacoes/sincroniaesocialconsulta.py
nsj_pyRPA/nasajonRPA/automacoes/sincroniaesocialenvio.py
nsj_pyRPA/nasajonRPA/controller/__init__.py
nsj_pyRPA/nasajonRPA/controller/automacoesempresas.py
nsj_pyRPA/nasajonRPA/controller/controllerBase.py
nsj_pyRPA/nasajonRPA/controller/rotinaautomatizada.py
nsj_pyRPA/nasajonRPA/dto/__init__.py
nsj_pyRPA/nasajonRPA/dto/rotinaautomatizada.py
nsj_pyRPA/nasajonRPA/entity/__init__.py
nsj_pyRPA/nasajonRPA/entity/automacaoempresa.py
nsj_pyRPA/nasajonRPA/entity/automacaoempresaparametro.py
nsj_pyRPA/nasajonRPA/entity/rotinaautomatizada.py
nsj_pyRPA/nasajonRPA/rotinas/__init__.py
nsj_pyRPA/nasajonRPA/rotinas/configuracoes.py
nsj_pyRPA/repositories/__init__.py
nsj_pyRPA/repositories/company_repository.py
nsj_pyRPA/repositories/company_settings_repository.py
nsj_pyRPA/repositories/notification_team_assignment_repository.py
nsj_pyRPA/repositories/notification_team_repository.py
nsj_pyRPA/resources/__init__.py
nsj_pyRPA/resources/automation_types.py
nsj_pyRPA/resources/conexao_banco.py
nsj_pyRPA/resources/const.py
nsj_pyRPA/resources/criptografia_erp2.py
nsj_pyRPA/resources/db_adapter3.py
nsj_pyRPA/resources/envConfig.py
nsj_pyRPA/resources/locking_banco.py
nsj_pyRPA/resources/log.py
nsj_pyRPA/resources/logconsumoapi.py
nsj_pyRPA/resources/utils.py
nsj_automacoesempresas-2.2601.0.1.dist-info/METADATA
nsj_automacoesempresas-2.2601.0.1.dist-info/WHEEL
nsj_automacoesempresas-2.2601.0.1.dist-info/top_level.txt
nsj_automacoesempresas-2.2601.0.1.dist-info/RECORD
