Metadata-Version: 2.4
Name: nsj_automacoesempresas
Version: 2.2601.0.1
Summary: Client em Python desenvolvido para orquestrar cálculos do RPA Nasajon.
Home-page: https://github.com/Nasajon/pyRPA
Author: Nasajon Sistemas
Author-email: contact.dev@nasajon.com.br
Project-URL: Source, https://github.com/Nasajon/pyRPA
Classifier: Development Status :: 3 - Alpha
Classifier: Intended Audience :: Developers
Classifier: Topic :: Software Development :: Libraries
Classifier: Programming Language :: Python :: 3
Requires-Python: >=3.8
Requires-Dist: SQLAlchemy==1.4.32
Requires-Dist: pg8000==1.24.1
Requires-Dist: sqlparams==3.0.0
Requires-Dist: python-dotenv==0.21.1
Requires-Dist: pywin32==306
Requires-Dist: nsj_rest_lib>=2.13.0a16
Requires-Dist: nsj_gcf_utils>=1.0.22
Requires-Dist: urllib3==1.26.16
Requires-Dist: python-dateutil==2.8.0
Requires-Dist: croniter==6.0.0
Requires-Dist: PyQt5==5.15.11
